adx_arrow-0.0.1.dist-info/METADATA
adx_arrow-0.0.1.dist-info/WHEEL
arrow_adx/__init__.py
arrow_adx/_internal.abi3.so
adx_arrow-0.0.1.dist-info/RECORD
