Metadata-Version: 2.1
Name: adx-arrow
Version: 0.0.1
Summary: High performance Kusto (Azure Data Explorer) client based on Apache Arrow and Rust.
Keywords: arrow,azure,adx,kusto
Author: Robert Pack <robstar.pack@gmail.com>
Author-email: Robert Pack <robstar.pack@gmail.com>
License: MIT License
Requires-Python: >=3.7
